{"coord":{"lon":-123.05,"lat":47.1},"weather":[{"id":800,"main":"Clear","description":"clear sky","icon":"01n"}],"base":"stations","main":{"temp":276.22,"feels_like":275.01,"temp_min":273.12,"temp_max":280.07,"pressure":1029,"humidity":93,"sea_level":1029,"grnd_level":1024},"visibility":10000,"wind":{"speed":1.42,"deg":34,"gust":1.63},"clouds":{"all":2},"dt":1668488165,"sys":{"type":2,"id":2072858,"country":"US","sunrise":1668438880,"sunset":1668472732},"timezone":-28800,"id":5805687,"name":"Olympia","cod":200}
